chromatograpy/__init__.py
chromatograpy/baseline/__init__.py
chromatograpy/baseline/airpls.py
chromatograpy/chromatogram.py
chromatograpy/identification/__init__.py
chromatograpy/io/__init__.py
chromatograpy/io/chromeleon_csv.py
chromatograpy/io/masslynx.py
chromatograpy/io/wrapper.py
chromatograpy/peaks/__init__.py
chromatograpy/peaks/peak.py
chromatograpy/peaks/prominence_based.py
chromatograpy/plot.py
chromatograpy/quantification/__init__.py
chromatograpy/quantification/wrapper.py
chromatograpy-0.1.0.dist-info/METADATA
chromatograpy-0.1.0.dist-info/WHEEL
chromatograpy-0.1.0.dist-info/licenses/LICENSE
chromatograpy-0.1.0.dist-info/RECORD
