Metadata-Version: 2.4
Name: chromatograpy
Version: 0.1.0
Summary: Library to analyze chromatograms
License: MIT
License-File: LICENSE
Author: c.moevus@gmail.com
Requires-Python: >=3.13
Classifier: License :: OSI Approved :: MIT License
Classifier: Programming Language :: Python :: 3
Classifier: Programming Language :: Python :: 3.13
Classifier: Programming Language :: Python :: 3.14
Requires-Dist: matplotlib
Requires-Dist: numpy
Requires-Dist: pandas
Requires-Dist: rainbow-api
Requires-Dist: scipy
